project94/__init__.py
project94/__main__.py
project94/project94.py
project94/session.py
project94/cli_commands/__init__.py
project94/cli_commands/base_command.py
project94/cli_commands/bind_shell.py
project94/cli_commands/cmd.py
project94/cli_commands/command.py
project94/cli_commands/encoding.py
project94/cli_commands/exit.py
project94/cli_commands/goto.py
project94/cli_commands/help.py
project94/cli_commands/info.py
project94/cli_commands/interact.py
project94/cli_commands/kill.py
project94/cli_commands/multiply_command.py
project94/cli_commands/sessions.py
project94/cli_commands/show.py
project94/utils/__init__.py
project94/utils/banners.py
project94/utils/completer.py
project94/utils/networking.py
project94/utils/printer.py
project94-1.1.dist-info/LICENSE
project94-1.1.dist-info/METADATA
project94-1.1.dist-info/WHEEL
project94-1.1.dist-info/entry_points.txt
project94-1.1.dist-info/top_level.txt
project94-1.1.dist-info/RECORD
