Metadata-Version: 2.1
Name: project94
Version: 1.1
Summary: Reverse shell manager
Home-page: https://github.com/d35ync/project94
Author: D35YNC
License: UNKNOWN
Platform: UNKNOWN
Classifier: Development Status :: 5 - Production/Stable
Classifier: Environment :: Console
Classifier: License :: OSI Approved :: MIT License
Classifier: Topic :: Security
Classifier: Programming Language :: Python
Classifier: Programming Language :: Python :: 3.10
Requires-Python: >=3.10
License-File: LICENSE
Requires-Dist: requests (==2.28.2)
